README.md
setup.py
Scripts/plotxmcd
Scripts/plotxmcd.bat
Scripts/xcirculardichro
Scripts/xcirculardichro.bat
xcirculardichro/__init__.py
xcirculardichro/__main__.py
xcirculardichro/test.py
xcirculardichro/treeExample.py
xcirculardichro/xmcdMain.py
xcirculardichro.egg-info/PKG-INFO
xcirculardichro.egg-info/SOURCES.txt
xcirculardichro.egg-info/dependency_links.txt
xcirculardichro.egg-info/requires.txt
xcirculardichro.egg-info/top_level.txt
xcirculardichro/_spec2nexus/__init__.py
xcirculardichro/_spec2nexus/plugins/__init__.py
xcirculardichro/_spec2nexus/plugins/qvaliadorexample.py
xcirculardichro/_spec2nexus/plugins/specuserplugin_spec2nexus.py
xcirculardichro/config/__init__.py
xcirculardichro/config/appconfigparser.py
xcirculardichro/data/__init__.py
xcirculardichro/data/datanode.py
xcirculardichro/data/filedatanode.py
xcirculardichro/data/intermediatedatanode.py
xcirculardichro/data/intermediatescannode.py
xcirculardichro/data/scandatanode.py
xcirculardichro/data/specfiledatanode.py
xcirculardichro/data/specscannode.py
xcirculardichro/gui/__init__.py
xcirculardichro/gui/datatype.py
xcirculardichro/gui/plotwidget.py
xcirculardichro/gui/xmcddatanavigator.py
xcirculardichro/gui/xmcdmainwindow.py
xcirculardichro/gui/choices/__init__.py
xcirculardichro/gui/choices/abstractchoices.py
xcirculardichro/gui/choices/choiceholder.py
xcirculardichro/gui/choices/escanchoices.py
xcirculardichro/gui/choices/intermediatechoices.py
xcirculardichro/gui/choices/lockinxmcdchoices.py
xcirculardichro/gui/choices/multinonlockinxmcdchoices.py
xcirculardichro/gui/choices/nonlockinxmcdchoices.py
xcirculardichro/gui/choices/qxscangeneric.py
xcirculardichro/gui/choices/undefinedchoices.py
xcirculardichro/gui/dataselection/AbstractSelectionDisplay.py
xcirculardichro/gui/dataselection/__init__.py
xcirculardichro/gui/dataselection/dummyselectiondisplay.py
xcirculardichro/gui/dataselection/intermediatedataselection.py
xcirculardichro/gui/dataselection/pointselectioninfo.py
xcirculardichro/gui/dataselection/rangeselectioninfo.py
xcirculardichro/gui/dataselection/selectionholder.py
xcirculardichro/gui/dataselection/specdisplay.py
xcirculardichro/gui/model/__init__.py
