Metadata-Version: 1.2
Name: xcirculardichro
Version: 0.9.4
Summary: Library to provide PyQt5 widgets to display spec file information read using spec2nexus.spec file library
Home-page: UNKNOWN
Author: John Hammonds
Author-email: JPHammonds@anl.gov
License: See LICENSE File
Platform: any
Requires-Python: >=3.5, <4
